MojangAPI/Client.py
MojangAPI/DataService.py
MojangAPI/Endpoints.py
MojangAPI/Errors.py
MojangAPI/Request.py
MojangAPI/Tokens.py
MojangAPI/__init__.py
MojangAPI-0.0.5.dist-info/METADATA
MojangAPI-0.0.5.dist-info/WHEEL
MojangAPI-0.0.5.dist-info/top_level.txt
MojangAPI-0.0.5.dist-info/RECORD
