Metadata-Version: 2.1
Name: MojangAPI
Version: 0.0.5
Summary: An async python wrapper for Mojangs API and Authentication API
Home-page: https://github.com/Jack92829/Mojang-API-Wrapper
Author: Jack92829
License: UNKNOWN
Project-URL: Issue tracker, https://github.com/Jack92829/Mojang-API-Wrapper/issues
Project-URL: Documentation, https://github.com/Jack92829/Mojang-API-Wrapper/blob/master/Docs.md
Platform: UNKNOWN
Classifier: Programming Language :: Python :: 3
Classifier: License :: OSI Approved :: MIT License
Classifier: Operating System :: OS Independent
Requires-Python: >=3.7
